sapioseleniumlib/__init__.py
sapioseleniumlib/script/__init__.py
sapioseleniumlib/script/noplate_sample_manifest.xlsx
sapioseleniumlib/script/truseq_dna.py
sapioseleniumlib/util/__init__.py
sapioseleniumlib/util/driver.py
sapioseleniumlib/util/ops.py
sapioseleniumlib/util/script.py
sapioseleniumlib/widgets/__init__.py
sapioseleniumlib/widgets/dialogs.py
sapioseleniumlib/widgets/do.py
sapioseleniumlib/widgets/eln.py
sapioseleniumlib/widgets/pagedef.py
sapioseleniumlib/widgets/pages.py
sapioseleniumlib/widgets/panels.py
sapioseleniumlib/widgets/toolbars.py
sapioseleniumlib/widgets/windowobj.py
sapioseleniumlib-2023.12.11.8.dist-info/METADATA
sapioseleniumlib-2023.12.11.8.dist-info/WHEEL
sapioseleniumlib-2023.12.11.8.dist-info/licenses/LICENSE
sapioseleniumlib-2023.12.11.8.dist-info/RECORD
