Metadata-Version: 2.1
Name: sapioseleniumlib
Version: 2023.12.11.8
Summary: Official Sapio Selenium Library
Project-URL: Homepage, https://github.com/sapiosciences
Author-email: Dereck Welch <dwelch@sapiosciences.com>, Yechen Qiao <yqiao@sapiosciences.com>
License-File: LICENSE
Keywords: eln,lims,sapio,testing
Classifier: Intended Audience :: Developers
Classifier: Intended Audience :: Healthcare Industry
Classifier: Intended Audience :: Science/Research
Classifier: License :: OSI Approved :: Mozilla Public License 2.0 (MPL 2.0)
Classifier: Operating System :: OS Independent
Classifier: Programming Language :: Python :: 3.10
Classifier: Topic :: Scientific/Engineering :: Bio-Informatics
Classifier: Topic :: Software Development :: Libraries :: Python Modules
Requires-Python: >=3.10
Requires-Dist: selenium>=4.13
Requires-Dist: webdriver-manager>=4.0.1
